anilistpy/__init__.py
anilistpy/anime.py
anilistpy/char.py
anilistpy/manga.py
anilistpy/staff.py
anilistpy/studio.py
anilistpy/utils.py
anilistpy/mutation/__init__.py
anilistpy/mutation/media.py
anilistpy/mutation/user.py
anilistpy/search/__init__.py
anilistpy/search/anime.py
anilistpy/search/char.py
anilistpy/search/manga.py
anilistpy/search/staff.py
anilistpy/search/studio.py
anilistpy/user/__init__.py
anilistpy/user/medialist.py
anilistpy-0.0.5.2.dist-info/METADATA
anilistpy-0.0.5.2.dist-info/WHEEL
anilistpy-0.0.5.2.dist-info/top_level.txt
anilistpy-0.0.5.2.dist-info/RECORD
