Metadata-Version: 2.1
Name: anilistpy
Version: 0.0.5.2
Summary: python API wrapper for anilist.co
Home-page: https://github.com/anilistpy/anilistpy
Author: kalekale
Author-email: kalekale.anon@gmail.com
License: UNKNOWN
Platform: UNKNOWN
Classifier: Programming Language :: Python :: 3
Classifier: License :: OSI Approved :: GNU Affero General Public License v3
Classifier: Operating System :: OS Independent
Requires-Python: >=3.6
